<?xml version="1.0"?>
<!DOCTYPE hibernate-mapping PUBLIC
	"-//Hibernate/Hibernate Mapping DTD//EN"
	"http://hibernate.sourceforge.net/hibernate-mapping-3.0.dtd" >

<hibernate-mapping package="jkt.hms.masters.business">
	<class name="StoreTenderM" table="store_tender_m">
		<meta attribute="sync-DAO">false</meta>
		<id name="Id" type="integer" column="id">
			<generator class="sequence">
				<param name="sequence">store_tender_m_id_seq</param>
			</generator>
		</id>

		<property name="TenderNo" column="tender_no" type="string"
			not-null="false" length="75" />
		<property name="TenderInvitationDate" column="tender_invitation_date"
			type="date" not-null="false" />
		<property name="CommOfIssueDate" column="comm_of_issue_date"
			type="date" not-null="false" />
		<property name="IssueLastDate" column="issue_last_date" type="date"
			not-null="false" />
		<property name="TenderReceiptTime" column="tender_receipt_time"
			type="string" not-null="false" length="15" />
		<property name="TenderReceiptPlace" column="tender_receipt_place"
			type="string" not-null="false" length="300" />
		<property name="TenderRecLastDate" column="tender_rec_last_date"
			type="date" not-null="false" />
		<property name="TenderRecLastTime" column="tender_rec_last_time"
			type="string" not-null="false" length="10" />
		<property name="TechnicalOpeningDate" column="technical_opening_date"
			type="date" not-null="false" />
		<property name="CommercialOpeningDate" column="commercial_opening_date"
			type="date" not-null="false" />
		<property name="AddressOfCommunication" column="address_of_communication"
			type="string" not-null="false" length="300" />
		<property name="Remarks" column="remarks" type="string"
			not-null="false" length="100" />
		<property name="TermsAndConditions" column="terms_and_conditions"
			type="string" not-null="false" length="512" />
		<property name="LastChangedBy" column="last_changed_by" type="string"
			not-null="false" length="12" />
		<property name="LastChangedDate" column="last_changed_date"
			type="date" not-null="false" />
		<property name="LastChangedTime" column="last_changed_time"
			type="string" not-null="false" length="10" />
		<property name="Status" column="status" type="string"
			not-null="false" length="1" />
		<many-to-one name="Hospital" column="hospital_id" class="MasHospital"
			not-null="false">
		</many-to-one>
		<many-to-one name="Department" column="department_id"
			class="MasDepartment" not-null="false">
		</many-to-one>
		<many-to-one name="Group" column="group_id" class="MasStoreGroup"
			not-null="false">
		</many-to-one>

		<set name="StoreTenderTs" inverse="true">
			<key column="id" />
			<one-to-many class="StoreTenderT" />
		</set>


	</class>
</hibernate-mapping>